walloc/__init__.py
walloc/walloc.py
walloc-1.2.1.dist-info/METADATA
walloc-1.2.1.dist-info/WHEEL
walloc-1.2.1.dist-info/top_level.txt
walloc-1.2.1.dist-info/RECORD
