Metadata-Version: 2.1
Name: walloc
Version: 1.2.1
Summary: Wavelet Learned Lossy Compression
Author-email: Dan Jacobellis <danjacobellis@utexas.edu>
Classifier: Programming Language :: Python :: 3
Classifier: Operating System :: OS Independent
Requires-Python: >=3.6
Requires-Dist: torch
Requires-Dist: einops
Requires-Dist: PyWavelets
Requires-Dist: pytorch-wavelets
Requires-Dist: diffusers
